yi_core/__init__.py
yi_core/lib.py
yi_core-0.1.0.dist-info/METADATA
yi_core-0.1.0.dist-info/WHEEL
yi_core-0.1.0.dist-info/RECORD
