Metadata-Version: 2.1
Name: yi-core
Version: 0.1.0
Summary: 
Author: Henry.Huang
Author-email: hhglory@outlook.com
Requires-Python: >=3.10,<4.0
Classifier: Programming Language :: Python :: 3
Classifier: Programming Language :: Python :: 3.10
Classifier: Programming Language :: Python :: 3.11
Classifier: Programming Language :: Python :: 3.12
Requires-Dist: loguru (>=0.7.2,<0.8.0)
